{
  "meta": {
    "smbc_url": "https://pc.moppy.jp/entry/invite.php?invite=Gupre100&s_id=149052",
    "smbc_catch": "三井住友カード（NL）新規クレジットカード発行で3,000P",
    "mufg_url": "https://pc.moppy.jp/entry/invite.php?invite=Gupre100&s_id=159811",
    "mufg_catch": "新規アプリダウンロード＋口座開設完了＋新規クレジットカード発行完了で12,000P"
  },
  "stores": [
    {
      "name": "セイコーマート",
      "group": "セコマグループ",
      "aliases": [
        "せいこーまーと",
        "セコマ",
        "せこま",
        "タイエー",
        "たいえー",
        "ハセガワストア",
        "はせがわすとあ",
        "ハセスト",
        "ハマナスクラブ",
        "はまなすくらぶ"
      ],
      "conditions": {
        "payment_method": "スマホのタッチ決済（Visa/Mastercard）のみ対象",
        "mobile_order": "対象外",
        "delivery": "対象外",
        "note": "商業施設内の店舗は対象外の場合あり。タイエー、ハセガワストア、ハマナスクラブも対象。カード現物、iD、カード差し込み、磁気取引は対象外。"
      },
      "official_list_url": null,
      "card_type": "SMBC",
      "source_url": "https://www.smbc-card.com/mem/wp/vpoint_up_program/index.jsp"
    },
    {
      "name": "セブン-イレブン",
      "group": "セブン&アイ・ホールディングス",
      "aliases": [
        "せぶんいれぶん",
        "セブン",
        "せぶん",
        "セブイレ",
        "せぶいれ",
        "セブンイレブン"
      ],
      "conditions": {
        "payment_method": "スマホのタッチ決済（Visa/Mastercard）のみ対象",
        "mobile_order": "対象外",
        "delivery": "対象外",
        "note": "商業施設内の店舗は対象外の場合あり。カード現物、iD、カード差し込み、磁気取引は対象外。"
      },
      "official_list_url": null,
      "card_type": "SMBC",
      "source_url": "https://www.smbc-card.com/mem/wp/vpoint_up_program/index.jsp"
    },
    {
      "name": "ポプラ",
      "group": "ポプラ",
      "aliases": [
        "ぽぷら",
        "生活彩家",
        "せいかつさいか"
      ],
      "conditions": {
        "payment_method": "スマホのタッチ決済（Visa/Mastercard）のみ対象",
        "mobile_order": "対象外",
        "delivery": "対象外",
        "note": "商業施設内の店舗は対象外の場合あり。生活彩家も対象。カード現物、iD、カード差し込み、磁気取引は対象外。"
      },
      "official_list_url": null,
      "card_type": "SMBC",
      "source_url": "https://www.smbc-card.com/mem/wp/vpoint_up_program/index.jsp"
    },
    {
      "name": "ミニストップ",
      "group": "イオングループ",
      "aliases": [
        "みにすとっぷ",
        "ミニスト",
        "みにすと"
      ],
      "conditions": {
        "payment_method": "スマホのタッチ決済（Visa/Mastercard）のみ対象",
        "mobile_order": "対象外",
        "delivery": "対象外",
        "note": "商業施設内の店舗は対象外の場合あり. カード現物、iD、カード差し込み、磁気取引は対象外。"
      },
      "official_list_url": null,
      "card_type": "SMBC",
      "source_url": "https://www.smbc-card.com/mem/wp/vpoint_up_program/index.jsp"
    },
    {
      "name": "ローソン",
      "group": "ローソングループ",
      "aliases": [
        "ろーそん",
        "ナチュラルローソン",
        "なちゅらるろーそん",
        "ローソンストア100",
        "ろーそんすとあひゃく",
        "100円ローソン",
        "ローソンスリーエフ",
        "ろーそんすりーえふ"
      ],
      "conditions": {
        "payment_method": "スマホのタッチ決済（Visa/Mastercard）のみ対象",
        "mobile_order": "対象外",
        "delivery": "対象外",
        "note": "商業施設内の店舗は対象外の場合あり。ナチュラルローソン、ローソンストア100、ローソンスリーエフも対象。カード現物、iD、カード差し込み、磁気取引は対象外。"
      },
      "official_list_url": null,
      "card_type": "SMBC",
      "source_url": "https://www.smbc-card.com/mem/wp/vpoint_up_program/index.jsp"
    },
    {
      "name": "マクドナルド",
      "group": "日本マクドナルド",
      "aliases": [
        "まくどなるど",
        "マック",
        "まっく",
        "マクド",
        "まくど",
        "Mac",
        "McDonald's"
      ],
      "conditions": {
        "payment_method": "スマホのタッチ決済（Visa/Mastercard）のみ対象",
        "mobile_order": "公式アプリのモバイルオーダー対象",
        "delivery": "対象外",
        "note": "商業施設内の店舗は対象外の場合あり。カード現物、iD、カード差し込み、磁気取引は対象外。"
      },
      "official_list_url": null,
      "card_type": "SMBC",
      "source_url": "https://www.smbc-card.com/mem/wp/vpoint_up_program/index.jsp"
    },
    {
      "name": "モスバーガー",
      "group": "モスフードサービス",
      "aliases": [
        "もすばーがー",
        "モス",
        "もす",
        "モスバーガー＆カフェ",
        "もすばーがーあんどかふぇ"
      ],
      "conditions": {
        "payment_method": "スマホのタッチ決済（Visa/Mastercard）のみ対象",
        "mobile_order": "公式アプリのモバイルオーダー対象",
        "delivery": "自社デリバリーは対象（他社サービス経由は対象外）",
        "note": "商業施設内の店舗は対象外の場合あり。モスバーガー＆カフェも対象。カード現物、iD、カード差し込み、磁気取引は対象外。"
      },
      "official_list_url": null,
      "card_type": "SMBC",
      "source_url": "https://www.smbc-card.com/mem/wp/vpoint_up_program/index.jsp"
    },
    {
      "name": "ケンタッキーフライドチキン",
      "group": "日本ケンタッキー・フライド・チキン",
      "aliases": [
        "けんたっきーふらいどちきん",
        "ケンタッキー",
        "けんたっきー",
        "ケンタ",
        "けんた",
        "KFC"
      ],
      "conditions": {
        "payment_method": "スマホのタッチ決済（Visa/Mastercard）のみ対象",
        "mobile_order": "公式アプリのモバイルオーダー対象",
        "delivery": "自社デリバリーは対象（他社サービス経由は対象外）",
        "note": "商業施設内の店舗は対象外の場合あり。カード現物、iD、カード差し込み、磁気取引は対象外。"
      },
      "official_list_url": null,
      "card_type": "SMBC",
      "source_url": "https://www.smbc-card.com/mem/wp/vpoint_up_program/index.jsp"
    },
    {
      "name": "吉野家",
      "group": "吉野家ホールディングス",
      "aliases": [
        "よしのや",
        "吉牛",
        "よしぎゅう",
        "よしの家"
      ],
      "conditions": {
        "payment_method": "スマホのタッチ決済（Visa/Mastercard）のみ対象",
        "mobile_order": "公式アプリのモバイルオーダー対象",
        "delivery": "対象外",
        "note": "商業施設内の店舗は対象外の場合あり。カード現物、iD、カード差し込み、磁気取引は対象外。"
      },
      "official_list_url": null,
      "card_type": "SMBC",
      "source_url": "https://www.smbc-card.com/mem/wp/vpoint_up_program/index.jsp"
    },
    {
      "name": "サイゼリヤ",
      "group": "サイゼリヤ",
      "aliases": [
        "さいぜりや",
        "サイゼ",
        "さいぜ"
      ],
      "conditions": {
        "payment_method": "スマホのタッチ決済（Visa/Mastercard）のみ対象",
        "mobile_order": "対象外",
        "delivery": "対象外",
        "note": "商業施設内の店舗は対象外の場合あり。カード現物、iD、カード差し込み、磁気取引は対象外。"
      },
      "official_list_url": null,
      "card_type": "SMBC",
      "source_url": "https://www.smbc-card.com/mem/wp/vpoint_up_program/index.jsp"
    },
    {
      "name": "ガスト",
      "group": "すかいらーくグループ",
      "aliases": [
        "がすと"
      ],
      "conditions": {
        "payment_method": "スマホのタッチ決済（Visa/Mastercard）のみ対象",
        "mobile_order": "対象外",
        "delivery": "対象外",
        "note": "商業施設内の店舗は対象外の場合あり。カード現物、iD、カード差し込み、磁気取引は対象外。"
      },
      "official_list_url": null,
      "card_type": "SMBC",
      "source_url": "https://www.smbc-card.com/mem/wp/vpoint_up_program/index.jsp"
    },
    {
      "name": "バーミヤン",
      "group": "すかいらーくグループ",
      "aliases": [
        "ばーみやん",
        "バミ",
        "ばみ"
      ],
      "conditions": {
        "payment_method": "スマホのタッチ決済（Visa/Mastercard）のみ対象",
        "mobile_order": "対象外",
        "delivery": "対象外",
        "note": "商業施設内の店舗は対象外の場合あり。カード現物、iD、カード差し込み、磁気取引は対象外。"
      },
      "official_list_url": null,
      "card_type": "SMBC",
      "source_url": "https://www.smbc-card.com/mem/wp/vpoint_up_program/index.jsp"
    },
    {
      "name": "しゃぶ葉",
      "group": "すかいらーくグループ",
      "aliases": [
        "しゃぶよう",
        "しゃぶは"
      ],
      "conditions": {
        "payment_method": "スマホのタッチ決済（Visa/Mastercard）のみ対象",
        "mobile_order": "対象外",
        "delivery": "対象外",
        "note": "商業施設内の店舗は対象外の場合あり。カード現物、iD、カード差し込み、磁気取引は対象外。"
      },
      "official_list_url": null,
      "card_type": "SMBC",
      "source_url": "https://www.smbc-card.com/mem/wp/vpoint_up_program/index.jsp"
    },
    {
      "name": "ジョナサン",
      "group": "すかいらーくグループ",
      "aliases": [
        "じょなさん",
        "ジョナ",
        "じょな"
      ],
      "conditions": {
        "payment_method": "スマホのタッチ決済（Visa/Mastercard）のみ対象",
        "mobile_order": "対象外",
        "delivery": "対象外",
        "note": "商業施設内の店舗は対象外の場合あり。カード現物、iD、カード差し込み、磁気取引は対象外。"
      },
      "official_list_url": null,
      "card_type": "SMBC",
      "source_url": "https://www.smbc-card.com/mem/wp/vpoint_up_program/index.jsp"
    },
    {
      "name": "夢庵",
      "group": "すかいらーくグループ",
      "aliases": [
        "ゆめあん"
      ],
      "conditions": {
        "payment_method": "スマホのタッチ決済（Visa/Mastercard）のみ対象",
        "mobile_order": "対象外",
        "delivery": "対象外",
        "note": "商業施設内の店舗は対象外の場合あり。カード現物、iD、カード差し込み、磁気取引は対象外。"
      },
      "official_list_url": null,
      "card_type": "SMBC",
      "source_url": "https://www.smbc-card.com/mem/wp/vpoint_up_program/index.jsp"
    },
    {
      "name": "すき家",
      "group": "ゼンショーグループ",
      "aliases": [
        "すきや"
      ],
      "conditions": {
        "payment_method": "スマホのタッチ決済（Visa/Mastercard）のみ対象",
        "mobile_order": "公式アプリのモバイルオーダー対象",
        "delivery": "対象外",
        "note": "商業施設内の店舗は対象外の場合あり。カード現物、iD、カード差し込み、磁気取引は対象外。"
      },
      "official_list_url": null,
      "card_type": "SMBC",
      "source_url": "https://www.smbc-card.com/mem/wp/vpoint_up_program/index.jsp"
    },
    {
      "name": "はま寿司",
      "group": "ゼンショーグループ",
      "aliases": [
        "はまずし",
        "はま"
      ],
      "conditions": {
        "payment_method": "スマホのタッチ決済（Visa/Mastercard）のみ対象",
        "mobile_order": "対象外",
        "delivery": "対象外",
        "note": "商業施設内の店舗は対象外の場合あり。カード現物、iD、カード差し込み、磁気取引は対象外。"
      },
      "official_list_url": null,
      "card_type": "SMBC",
      "source_url": "https://www.smbc-card.com/mem/wp/vpoint_up_program/index.jsp"
    },
    {
      "name": "ココス",
      "group": "ゼンショーグループ",
      "aliases": [
        "ここす",
        "COCO'S"
      ],
      "conditions": {
        "payment_method": "スマホのタッチ決済（Visa/Mastercard）のみ対象",
        "mobile_order": "対象外",
        "delivery": "対象外",
        "note": "商業施設内の店舗は対象外の場合あり。カード現物、iD、カード差し込み、磁気取引は対象外。"
      },
      "official_list_url": null,
      "card_type": "SMBC",
      "source_url": "https://www.smbc-card.com/mem/wp/vpoint_up_program/index.jsp"
    },
    {
      "name": "ドトールコーヒーショップ",
      "group": "ドトール・日レスホールディングス",
      "aliases": [
        "どとーるこーひーしょっぷ",
        "ドトール",
        "どとーる"
      ],
      "conditions": {
        "payment_method": "スマホのタッチ決済（Visa/Mastercard）のみ対象",
        "mobile_order": "対象外",
        "delivery": "対象外",
        "note": "商業施設内の店舗は対象外の場合あり。カード現物、iD、カード差し込み、磁気取引は対象外。"
      },
      "official_list_url": null,
      "card_type": "SMBC",
      "source_url": "https://www.smbc-card.com/mem/wp/vpoint_up_program/index.jsp"
    },
    {
      "name": "エクセルシオール カフェ",
      "group": "ドトール・日レスホールディングス",
      "aliases": [
        "えくせるしおーるかふぇ",
        "エクセル",
        "えくせる"
      ],
      "conditions": {
        "payment_method": "スマホのタッチ決済（Visa/Mastercard）のみ対象",
        "mobile_order": "対象外",
        "delivery": "対象外",
        "note": "商業施設内の店舗は対象外の場合あり。カード現物、iD、カード差し込み、磁気取引は対象外。"
      },
      "official_list_url": null,
      "card_type": "SMBC",
      "source_url": "https://www.smbc-card.com/mem/wp/vpoint_up_program/index.jsp"
    },
    {
      "name": "かっぱ寿司",
      "group": "コロワイド",
      "aliases": [
        "かっぱずし",
        "かっぱ"
      ],
      "conditions": {
        "payment_method": "スマホのタッチ決済（Visa/Mastercard）のみ対象",
        "mobile_order": "対象外",
        "delivery": "対象外",
        "note": "商業施設内の店舗は対象外の場合あり。カード現物、iD、カード差し込み、磁気取引は対象外。"
      },
      "official_list_url": null,
      "card_type": "SMBC",
      "source_url": "https://www.smbc-card.com/mem/wp/vpoint_up_program/index.jsp"
    },
    {
      "name": "スターバックス",
      "group": "スターバックスコーヒージャパン",
      "aliases": [
        "すたーばっくす",
        "スタバ",
        "すたば",
        "Starbucks"
      ],
      "conditions": {
        "payment_method": "対象外（モバイルオーダーのみ対象）",
        "mobile_order": "Apple Payでの決済のみ対象",
        "delivery": "対象外",
        "note": "商業施設内の店舗は対象外の場合あり。モバイルオーダーかつApple Pay決済のみが対象。"
      },
      "official_list_url": null,
      "card_type": "SMBC",
      "source_url": "https://www.smbc-card.com/mem/wp/vpoint_up_program/index.jsp"
    },
    {
      "name": "すかいらーくグループ（その他対象店舗）",
      "group": "すかいらーくグループ",
      "aliases": [
        "すてーきがすと",
        "からよし",
        "むさしのもりこーひー",
        "あいや",
        "ぐらっちぇがーでんず",
        "ととかーじ",
        "ちゃわん",
        "らおはな",
        "とんからてい",
        "ゆめあんしょくどう",
        "とうさい",
        "はちろうそば",
        "みわみ",
        "ステーキガスト",
        "から好し",
        "むさしの森珈琲",
        "藍屋",
        "グラッチェガーデンズ",
        "魚屋路",
        "chawan",
        "La Ohana",
        "とんから亭",
        "ゆめあん食堂",
        "桃菜",
        "八郎そば",
        "三〇三"
      ],
      "conditions": {
        "payment_method": "スマホのタッチ決済（Visa/Mastercard）のみ対象",
        "mobile_order": "対象外",
        "delivery": "対象外",
        "note": "商業施設内の店舗は対象外の場合あり。対象店舗：ステーキガスト、から好し、むさしの森珈琲、藍屋、グラッチェガーデンズ、魚屋路、chawan、La Ohana、とんから亭、ゆめあん食堂、桃菜、八郎そば、三〇三。カード現物、iD、カード差し込み、磁気取引は対象外。"
      },
      "official_list_url": null,
      "card_type": "SMBC",
      "source_url": "https://www.smbc-card.com/mem/wp/vpoint_up_program/index.jsp"
    },
    {
      "name": "セブン‐イレブン",
      "group": null,
      "aliases": [
        "セブン",
        "セブイレ",
        "セブンイレブン",
        "せぶんいればん",
        "せぶん"
      ],
      "conditions": {
        "payment_method": "物理カード、物理カードタッチ決済、Apple Pay（QUICPay）のみ。スマホでのタッチ決済は対象外",
        "mobile_order": "対象外（スマホレジ、オンラインショッピングは対象外）",
        "delivery": "対象外",
        "note": "Amexは条件が異なる可能性があるため公式サイトを確認推奨。商業施設内の店舗は対象外の場合あり。セブン自販機は対象外。"
      },
      "official_list_url": null,
      "card_type": "MUFG",
      "source_url": "https://www.cr.mufg.jp/mufgcard/point/global/save/convenience_store/index.html"
    },
    {
      "name": "ローソン",
      "group": "ローソングループ",
      "aliases": [
        "ろーそん",
        "ローソンストア100",
        "ナチュラルローソン",
        "ローソン100",
        "なちゅらるろーそん"
      ],
      "conditions": {
        "payment_method": "物理カード、物理カードタッチ決済、Apple Pay（QUICPay）のみ。スマホでのタッチ決済は対象外",
        "mobile_order": "対象外（スマホレジ、オンラインショッピングは対象外）",
        "delivery": "対象外",
        "note": "Amexは条件が異なる可能性があるため公式サイトを確認推奨。商業施設内の店舗、駅ビル内店舗、ガソリンスタンド併設店舗などは対象外の場合あり。「ナチュラルローソン」「ローソンストア100」も対象。"
      },
      "official_list_url": null,
      "card_type": "MUFG",
      "source_url": "https://www.cr.mufg.jp/mufgcard/point/global/save/convenience_store/index.html"
    },
    {
      "name": "コカ・コーラ自販機",
      "group": "コカ・コーラ",
      "aliases": [
        "こかこーら",
        "コカコーラ",
        "Coke ON",
        "コークオン"
      ],
      "conditions": {
        "payment_method": "自販機上のタッチ決済（クレジットカード/QUICPay）、Coke ON Pay、Coke ON Pass（Apple Pay利用分は対象外）",
        "mobile_order": "Coke ONアプリでの決済は対象（Apple Payは対象外）",
        "delivery": "対象外",
        "note": "Amexは条件が異なる可能性があるため公式サイトを確認推奨。スマホでのタッチ決済は対象外。"
      },
      "official_list_url": null,
      "card_type": "MUFG",
      "source_url": "https://www.cr.mufg.jp/mufgcard/point/global/save/convenience_store/index.html"
    },
    {
      "name": "上島珈琲店",
      "group": "UCCグループ",
      "aliases": [
        "うえしまこーひー",
        "上島珈琲",
        "UCC Cafe Plaza",
        "ユーシーシー"
      ],
      "conditions": {
        "payment_method": "物理カード、物理カードタッチ決済、Apple Pay（QUICPay）のみ。スマホでのタッチ決済は対象外",
        "mobile_order": "不明",
        "delivery": "不明",
        "note": "Amexは条件が異なる可能性があるため公式サイトを確認推奨。商業施設内の店舗は対象外の場合あり。「UCC Cafe Plaza」も対象。"
      },
      "official_list_url": null,
      "card_type": "MUFG",
      "source_url": "https://www.cr.mufg.jp/mufgcard/point/global/save/convenience_store/index.html"
    },
    {
      "name": "カフェ・ド・クリエ",
      "group": "C-United",
      "aliases": [
        "かふぇどくりえ",
        "カフェドクリエ",
        "クリエ"
      ],
      "conditions": {
        "payment_method": "物理カード、物理カードタッチ決済、Apple Pay（QUICPay）のみ。スマホでのタッチ決済は対象外",
        "mobile_order": "対象外",
        "delivery": "不明",
        "note": "Amexは条件が異なる可能性があるため公式サイトを確認推奨。商業施設内の店舗は対象外の場合あり。クリエカードチャージは対象外。"
      },
      "official_list_url": null,
      "card_type": "MUFG",
      "source_url": "https://www.cr.mufg.jp/mufgcard/point/global/save/convenience_store/index.html"
    },
    {
      "name": "スターバックス",
      "group": "スターバックス コーヒー ジャパン",
      "aliases": [
        "すたーばっくす",
        "スタバ",
        "すたば",
        "Starbucks"
      ],
      "conditions": {
        "payment_method": "スターバックス カードへのオンライン入金のみ対象（店頭での入金・利用は対象外）",
        "mobile_order": "オンライン入金のみ対象",
        "delivery": "対象外",
        "note": "Amexは条件が異なる可能性があるため公式サイトを確認推奨。スマホでのタッチ決済は対象外。店頭決済は対象外。"
      },
      "official_list_url": null,
      "card_type": "MUFG",
      "source_url": "https://www.cr.mufg.jp/mufgcard/point/global/save/convenience_store/index.html"
    },
    {
      "name": "くら寿司",
      "group": "くら寿司",
      "aliases": [
        "くらずし",
        "無添くら寿司",
        "くら"
      ],
      "conditions": {
        "payment_method": "物理カード、物理カードタッチ決済、Apple Pay（QUICPay）のみ。スマホでのタッチ決済は対象外",
        "mobile_order": "対象外（スマホでお持ち帰り、どこでもくら寿司などのオンライン事前決済は対象外）",
        "delivery": "対象外",
        "note": "Amexは条件が異なる可能性があるため公式サイトを確認推奨。商業施設内の店舗（ららぽーとTOKYO-BAY店など）は対象外の場合あり。"
      },
      "official_list_url": null,
      "card_type": "MUFG",
      "source_url": "https://www.cr.mufg.jp/mufgcard/point/global/save/convenience_store/index.html"
    },
    {
      "name": "スシロー",
      "group": "FOOD & LIFE COMPANIES",
      "aliases": [
        "すしろー",
        "あきんどスシロー"
      ],
      "conditions": {
        "payment_method": "物理カード、物理カードタッチ決済、Apple Pay（QUICPay）のみ。スマホでのタッチ決済は対象外",
        "mobile_order": "対象外（オンライン決済は対象外）",
        "delivery": "対象外",
        "note": "Amexは条件が異なる可能性があるため公式サイトを確認推奨。商業施設内の店舗は対象外の場合あり。「京樽スシロー」「スシローToGo」は対象外。"
      },
      "official_list_url": null,
      "card_type": "MUFG",
      "source_url": "https://www.cr.mufg.jp/mufgcard/point/global/save/convenience_store/index.html"
    },
    {
      "name": "ピザハットオンライン",
      "group": "日本ピザハット",
      "aliases": [
        "ぴざはっと",
        "ピザハット",
        "Pizza Hut"
      ],
      "conditions": {
        "payment_method": "公式サイト・公式アプリでのオンライン注文時のクレジットカード決済のみ対象",
        "mobile_order": "公式アプリでのオンライン注文は対象",
        "delivery": "公式オンライン注文経由は対象",
        "note": "Amexは条件が異なる可能性があるため公式サイトを確認推奨。店頭決済は対象外。"
      },
      "official_list_url": null,
      "card_type": "MUFG",
      "source_url": "https://www.cr.mufg.jp/mufgcard/point/global/save/convenience_store/index.html"
    },
    {
      "name": "松屋・松のや・マイカリー食堂（店舗決済）",
      "group": "松屋フーズ",
      "aliases": [
        "まつや",
        "まつのや",
        "まいかりーしょくどう",
        "マイカリー"
      ],
      "conditions": {
        "payment_method": "店舗券売機・セルフレジでのクレジットカード決済、Apple Pay（QUICPay）",
        "mobile_order": "別サービス（松弁ネット等）で対象",
        "delivery": "別サービス（松弁デリバリー等）で対象",
        "note": "Amexは条件が異なる可能性があるため公式サイトを確認推奨。スマホでのタッチ決済は対象外。高速道路SA・PA内など一部対象外店舗あり。"
      },
      "official_list_url": null,
      "card_type": "MUFG",
      "source_url": "https://www.cr.mufg.jp/mufgcard/point/global/save/convenience_store/index.html"
    },
    {
      "name": "松弁ネット・松屋モバイルオーダー・松弁デリバリー",
      "group": "松屋フーズ",
      "aliases": [
        "まつべんねっと",
        "まつやもばいるおーだー",
        "まつべんでりばりー",
        "ステーキ屋松",
        "松軒中華食堂",
        "すし松",
        "トゥックントゥックン",
        "麦のトリコ",
        "松太郎"
      ],
      "conditions": {
        "payment_method": "ネット注文サービスでのクレジットカード決済",
        "mobile_order": "松弁ネット、松屋モバイルオーダーでの決済は対象",
        "delivery": "松弁デリバリーでの決済は対象",
        "note": "Amexは条件が異なる可能性があるため公式サイトを確認推奨。松屋公式オンラインショップは対象外。対象ブランド：松屋、松のや、マイカリー食堂、ステーキ屋松、松軒中華食堂、すし松、トゥックントゥックン、麦のトリコ、松太郎。"
      },
      "official_list_url": null,
      "card_type": "MUFG",
      "source_url": "https://www.cr.mufg.jp/mufgcard/point/global/save/convenience_store/index.html"
    },
    {
      "name": "ゼッテリア",
      "group": "ロッテリア",
      "aliases": [
        "ぜってりあ",
        "ZETTERIA"
      ],
      "conditions": {
        "payment_method": "店頭決済、公式アプリでのモバイルオーダーのクレジットカード決済",
        "mobile_order": "公式アプリでのモバイルオーダーは対象",
        "delivery": "不明",
        "note": "Amexは条件が異なる可能性があるため公式サイトを確認推奨。商業施設内の店舗は対象外の場合あり。スマホでのタッチ決済は対象外。"
      },
      "official_list_url": null,
      "card_type": "MUFG",
      "source_url": "https://www.cr.mufg.jp/mufgcard/point/global/save/convenience_store/index.html"
    },
    {
      "name": "アカチャンホンポ",
      "group": "セブン&アイ・ホールディングス",
      "aliases": [
        "あかちゃんほんぽ",
        "赤ちゃん本舗"
      ],
      "conditions": {
        "payment_method": "店頭決済（※Amexは対象外）、オンラインショップでのクレジットカード決済",
        "mobile_order": "オンラインショップは対象",
        "delivery": "不明",
        "note": "Amexは店頭決済対象外（オンラインショップは対象の可能性あり、要確認）。商業施設内の店舗やフランチャイズ店舗は対象外の場合あり。スマホでのタッチ決済は対象外。"
      },
      "official_list_url": null,
      "card_type": "MUFG",
      "source_url": "https://www.cr.mufg.jp/mufgcard/point/global/save/convenience_store/index.html"
    },
    {
      "name": "カーブス",
      "group": "カーブス",
      "aliases": [
        "かーぶす",
        "Curves"
      ],
      "conditions": {
        "payment_method": "入会金、月会費のクレジットカード決済",
        "mobile_order": "対象外",
        "delivery": "対象外",
        "note": "Amexは条件が異なる可能性があるため公式サイトを確認推奨。スマホでのタッチ決済は対象外。"
      },
      "official_list_url": null,
      "card_type": "MUFG",
      "source_url": "https://www.cr.mufg.jp/mufgcard/point/global/save/convenience_store/index.html"
    },
    {
      "name": "アオキスーパー",
      "group": "アオキスーパー",
      "aliases": [
        "あおきすーぱー"
      ],
      "conditions": {
        "payment_method": "物理カード、物理カードタッチ決済、Apple Pay（QUICPay）のみ。スマホでのタッチ決済は対象外",
        "mobile_order": "対象外",
        "delivery": "対象外（クイックコマース、インターネットは対象外）",
        "note": "Amexは条件が異なる可能性があるため公式サイトを確認推奨。ショッピングセンターアズパーク内の専門店・花いちばアズガーデン、お買い上げレジが違う売り場は対象外。"
      },
      "official_list_url": null,
      "card_type": "MUFG",
      "source_url": "https://www.cr.mufg.jp/mufgcard/point/global/save/convenience_store/index.html"
    },
    {
      "name": "フードストアあおき",
      "group": "あおき",
      "aliases": [
        "ふーどすとああおき",
        "フードストア青木"
      ],
      "conditions": {
        "payment_method": "物理カード、物理カードタッチ決済、Apple Pay（QUICPay）のみ。スマホでのタッチ決済は対象外",
        "mobile_order": "対象外",
        "delivery": "対象外（ネットスーパーは対象外）",
        "note": "Amexは条件が異なる可能性があるため公式サイトを確認推奨。"
      },
      "official_list_url": null,
      "card_type": "MUFG",
      "source_url": "https://www.cr.mufg.jp/mufgcard/point/global/save/convenience_store/index.html"
    },
    {
      "name": "オーケー",
      "group": "オーケー",
      "aliases": [
        "おーけー",
        "オーケーストア",
        "OKストア"
      ],
      "conditions": {
        "payment_method": "物理カード、物理カードタッチ決済、Apple Pay（QUICPay）のみ。スマホでのタッチ決済は対象外",
        "mobile_order": "対象外",
        "delivery": "対象外（ネットスーパーは対象外）",
        "note": "Amexは条件が異なる可能性があるため公式サイトを確認推奨。"
      },
      "official_list_url": null,
      "card_type": "MUFG",
      "source_url": "https://www.cr.mufg.jp/mufgcard/point/global/save/convenience_store/index.html"
    },
    {
      "name": "オオゼキ",
      "group": "オオゼキ",
      "aliases": [
        "おおぜき"
      ],
      "conditions": {
        "payment_method": "物理カード、物理カードタッチ決済、Apple Pay（QUICPay）のみ。スマホでのタッチ決済は対象外",
        "mobile_order": "対象外",
        "delivery": "対象外（オンラインストア、ネットスーパーは対象外）",
        "note": "Amexは条件が異なる可能性があるため公式サイトを確認推奨。"
      },
      "official_list_url": null,
      "card_type": "MUFG",
      "source_url": "https://www.cr.mufg.jp/mufgcard/point/global/save/convenience_store/index.html"
    },
    {
      "name": "サンリブ",
      "group": "サンリブグループ",
      "aliases": [
        "さんりぶ",
        "マルショク",
        "まるしょく",
        "リブホール",
        "サンク",
        "サンリブBUONO"
      ],
      "conditions": {
        "payment_method": "物理カード、物理カードタッチ決済、Apple Pay（QUICPay）のみ。スマホでのタッチ決済は対象外",
        "mobile_order": "対象外",
        "delivery": "対象外（ネットスーパーは対象外）",
        "note": "Amexは条件が異なる可能性があるため公式サイトを確認推奨。「マルショク」「リブホール」「サンク」「サンリブBUONO」も対象。"
      },
      "official_list_url": null,
      "card_type": "MUFG",
      "source_url": "https://www.cr.mufg.jp/mufgcard/point/global/save/convenience_store/index.html"
    },
    {
      "name": "三和・フードワン",
      "group": "三和",
      "aliases": [
        "さんわ",
        "ふーどわん",
        "フードワン",
        "スーパー三和"
      ],
      "conditions": {
        "payment_method": "物理カード、物理カードタッチ決済、Apple Pay（QUICPay）のみ。スマホでのタッチ決済は対象外",
        "mobile_order": "対象外",
        "delivery": "対象外",
        "note": "Amexは条件が異なる可能性があるため公式サイトを確認推奨。"
      },
      "official_list_url": null,
      "card_type": "MUFG",
      "source_url": "https://www.cr.mufg.jp/mufgcard/point/global/save/convenience_store/index.html"
    },
    {
      "name": "スーパー魚長",
      "group": "魚長",
      "aliases": [
        "すーぱーうおちょう",
        "魚長",
        "うおちょう",
        "生鮮乃木市場",
        "生鮮げんき市場"
      ],
      "conditions": {
        "payment_method": "物理カード、物理カードタッチ決済、Apple Pay（QUICPay）のみ。スマホでのタッチ決済は対象外",
        "mobile_order": "対象外",
        "delivery": "対象外",
        "note": "Amexは条件が異なる可能性があるため公式サイトを確認推奨。「生鮮乃木市場」「生鮮げんき市場」も対象。"
      },
      "official_list_url": null,
      "card_type": "MUFG",
      "source_url": "https://www.cr.mufg.jp/mufgcard/point/global/save/convenience_store/index.html"
    },
    {
      "name": "近商ストア",
      "group": "近鉄グループ",
      "aliases": [
        "きんしょうすとあ",
        "近商",
        "きんしょう",
        "ハーベス",
        "はーべす",
        "Pochette",
        "ぽしぇっと"
      ],
      "conditions": {
        "payment_method": "物理カード、物理カードタッチ決済、Apple Pay（QUICPay）のみ。スマホでのタッチ決済は対象外",
        "mobile_order": "対象外",
        "delivery": "対象外（ネットスーパーは対象外）",
        "note": "Amexは条件が異なる可能性があるため公式サイトを確認推奨。「ハーベス」「Pochette」も対象。食品スーパー以外は対象外。"
      },
      "official_list_url": null,
      "card_type": "MUFG",
      "source_url": "https://www.cr.mufg.jp/mufgcard/point/global/save/convenience_store/index.html"
    },
    {
      "name": "東急ストア",
      "group": "東急グループ",
      "aliases": [
        "とうきゅうすとあ",
        "東急",
        "とうきゅう",
        "プレッセ",
        "ぷれっせ",
        "フードステーション"
      ],
      "conditions": {
        "payment_method": "物理カード、物理カードタッチ決済、Apple Pay（QUICPay）のみ。スマホでのタッチ決済は対象外",
        "mobile_order": "対象外",
        "delivery": "対象外（ネットスーパーは対象外）",
        "note": "Amexは条件が異なる可能性があるため公式サイトを確認推奨。「プレッセ」「フードステーション」も対象。テナントは対象外。"
      },
      "official_list_url": null,
      "card_type": "MUFG",
      "source_url": "https://www.cr.mufg.jp/mufgcard/point/global/save/convenience_store/index.html"
    },
    {
      "name": "東武ストア",
      "group": "東武グループ",
      "aliases": [
        "とうぶすとあ",
        "東武",
        "とうぶ"
      ],
      "conditions": {
        "payment_method": "物理カード、物理カードタッチ決済、Apple Pay（QUICPay）のみ。スマホでのタッチ決済は対象外",
        "mobile_order": "対象外",
        "delivery": "対象外（ネットショップは対象外）",
        "note": "Amexは条件が異なる可能性があるため公式サイトを確認推奨。手ぶら決済、専門店売り場などは対象外。"
      },
      "official_list_url": null,
      "card_type": "MUFG",
      "source_url": "https://www.cr.mufg.jp/mufgcard/point/global/save/convenience_store/index.html"
    },
    {
      "name": "ドミー",
      "group": "ドミー",
      "aliases": [
        "どみー"
      ],
      "conditions": {
        "payment_method": "物理カード、物理カードタッチ決済、Apple Pay（QUICPay）のみ。スマホでのタッチ決済は対象外",
        "mobile_order": "対象外",
        "delivery": "対象外",
        "note": "Amexは条件が異なる可能性があるため公式サイトを確認推奨。"
      },
      "official_list_url": null,
      "card_type": "MUFG",
      "source_url": "https://www.cr.mufg.jp/mufgcard/point/global/save/convenience_store/index.html"
    },
    {
      "name": "肉のハナマサ",
      "group": "JMホールディングス",
      "aliases": [
        "にくのはなまさ",
        "ハナマサ",
        "はなまさ"
      ],
      "conditions": {
        "payment_method": "物理カード、物理カードタッチ決済、Apple Pay（QUICPay）のみ。スマホでのタッチ決済は対象外",
        "mobile_order": "対象外",
        "delivery": "対象外",
        "note": "Amexは条件が異なる可能性があるため公式サイトを確認推奨。フランチャイズ店は対象外。"
      },
      "official_list_url": null,
      "card_type": "MUFG",
      "source_url": "https://www.cr.mufg.jp/mufgcard/point/global/save/convenience_store/index.html"
    },
    {
      "name": "ジャパンミート",
      "group": "JMホールディングス",
      "aliases": [
        "じゃぱんみーと",
        "MEATMeet",
        "パワーマート",
        "ぱわーまーと"
      ],
      "conditions": {
        "payment_method": "物理カード、物理カードタッチ決済、Apple Pay（QUICPay）のみ。スマホでのタッチ決済は対象外",
        "mobile_order": "対象外",
        "delivery": "対象外",
        "note": "Amexは条件が異なる可能性があるため公式サイトを確認推奨。「MEATMeet」「パワーマート」も対象。"
      },
      "official_list_url": null,
      "card_type": "MUFG",
      "source_url": "https://www.cr.mufg.jp/mufgcard/point/global/save/convenience_store/index.html"
    },
    {
      "name": "フィール",
      "group": "フィールコーポレーション",
      "aliases": [
        "ふぃーる",
        "FEEL"
      ],
      "conditions": {
        "payment_method": "物理カード、物理カードタッチ決済、Apple Pay（QUICPay）のみ。スマホでのタッチ決済は対象外",
        "mobile_order": "対象外",
        "delivery": "対象外",
        "note": "Amexは条件が異なる可能性があるため公式サイトを確認推奨。テナント、インターネットでのご利用は対象外。"
      },
      "official_list_url": null,
      "card_type": "MUFG",
      "source_url": "https://www.cr.mufg.jp/mufgcard/point/global/save/convenience_store/index.html"
    },
    {
      "name": "ヤマナカ",
      "group": "ヤマナカ",
      "aliases": [
        "やまなか",
        "フランテ",
        "ふらんて",
        "フランテロゼ"
      ],
      "conditions": {
        "payment_method": "物理カード、物理カードタッチ決済、Apple Pay（QUICPay）のみ。スマホでのタッチ決済は対象外",
        "mobile_order": "対象外",
        "delivery": "対象外（ネットスーパーは対象外）",
        "note": "Amexは条件が異なる可能性があるため公式サイトを確認推奨。「フランテ」「フランテロゼ」も対象。"
      },
      "official_list_url": null,
      "card_type": "MUFG",
      "source_url": "https://www.cr.mufg.jp/mufgcard/point/global/save/convenience_store/index.html"
    }
  ]
}