{
  "meta": {
    "smbc_url": "https://pc.moppy.jp/entry/invite.php?invite=Gupre100&s_id=149052",
    "smbc_catch": "4/5まで過去最高15,000P還元",
    "mufg_url": "https://pc.moppy.jp/entry/invite.php?invite=Gupre100&s_id=159811",
    "mufg_catch": "カード発行で10,000P以上の高額ポイント獲得も可能"
  },
  "stores": [
    {
      "name": "セブン-イレブン",
      "group": null,
      "aliases": [
        "せぶんいれぶん",
        "セブン",
        "セブイレ",
        "7-11",
        "セブンイレブン"
      ],
      "conditions": {
        "payment_method": "物理カード、カードのタッチ決済、Apple Pay(QUICPay)が対象。スマホのタッチ決済は対象外。",
        "mobile_order": "対象外",
        "delivery": "対象外",
        "note": "商業施設内の店舗は対象外の場合あり。セブン自販機、スマホレジは対象外。Amexは条件が異なる可能性があるため公式サイトを確認推奨。"
      },
      "official_list_url": null,
      "card_type": "MUFG",
      "source_url": "https://www.cr.mufg.jp/mufgcard/point/global/save/convenience_store/index.html"
    },
    {
      "name": "ローソン",
      "group": null,
      "aliases": [
        "ろーそん",
        "ローソン",
        "ナチュラルローソン",
        "ローソンストア100",
        "なちゅらるろーそん",
        "ろーそんすとあ100"
      ],
      "conditions": {
        "payment_method": "物理カード、カードのタッチ決済、Apple Pay(QUICPay)が対象。スマホのタッチ決済は対象外。",
        "mobile_order": "対象外",
        "delivery": "対象外",
        "note": "商業施設内、駅ビル内、ガソリンスタンド併設店舗は対象外の場合あり。スマホレジ、自販機は対象外。Amexは条件が異なる可能性があるため公式サイトを確認推奨。"
      },
      "official_list_url": null,
      "card_type": "MUFG",
      "source_url": "https://www.cr.mufg.jp/mufgcard/point/global/save/convenience_store/index.html"
    },
    {
      "name": "コカ・コーラ自販機",
      "group": "日本コカ・コーラ",
      "aliases": [
        "こかこーらじはんき",
        "コカコーラ",
        "Coke ON",
        "コークオン",
        "こーくおん"
      ],
      "conditions": {
        "payment_method": "自販機上のタッチ決済（カード）、QUICPay、Coke ON Payが対象。",
        "mobile_order": "Coke ONアプリ経由の決済は対象",
        "delivery": null,
        "note": "Apple Pay利用分は対象外。Amexは条件が異なる可能性があるため公式サイトを確認推奨。"
      },
      "official_list_url": null,
      "card_type": "MUFG",
      "source_url": "https://www.cr.mufg.jp/mufgcard/point/global/save/convenience_store/index.html"
    },
    {
      "name": "くら寿司",
      "group": "くら寿司",
      "aliases": [
        "くらずし",
        "無添くら寿司",
        "むてんくらずし"
      ],
      "conditions": {
        "payment_method": "物理カード、カードのタッチ決済、Apple Pay(QUICPay)が対象。スマホのタッチ決済は対象外。",
        "mobile_order": "対象外（オンライン事前決済）",
        "delivery": "対象外",
        "note": "商業施設内の店舗（ららぽーとTOKYO-BAY店など）は対象外の場合あり。Amexは条件が異なる可能性があるため公式サイトを確認推奨。"
      },
      "official_list_url": null,
      "card_type": "MUFG",
      "source_url": "https://www.cr.mufg.jp/mufgcard/point/global/save/convenience_store/index.html"
    },
    {
      "name": "スシロー",
      "group": "FOOD & LIFE COMPANIES",
      "aliases": [
        "すしろー",
        "あきんどスシロー"
      ],
      "conditions": {
        "payment_method": "物理カード、カードのタッチ決済、Apple Pay(QUICPay)が対象。スマホのタッチ決済は対象外。",
        "mobile_order": "対象外（オンライン決済）",
        "delivery": null,
        "note": "商業施設内の店舗は対象外の場合あり。京樽スシロー、スシローToGoは対象外。Amexは条件が異なる可能性があるため公式サイトを確認推奨。"
      },
      "official_list_url": null,
      "card_type": "MUFG",
      "source_url": "https://www.cr.mufg.jp/mufgcard/point/global/save/convenience_store/index.html"
    },
    {
      "name": "ピザハットオンライン",
      "group": "日本ピザハット",
      "aliases": [
        "ぴざはっと",
        "ピザハット"
      ],
      "conditions": {
        "payment_method": "公式サイト・公式アプリでのクレジットカード決済のみ対象。",
        "mobile_order": "公式アプリ対象",
        "delivery": "自社デリバリー対象",
        "note": "Amexは条件が異なる可能性があるため公式サイトを確認推奨。"
      },
      "official_list_url": null,
      "card_type": "MUFG",
      "source_url": "https://www.cr.mufg.jp/mufgcard/point/global/save/convenience_store/index.html"
    },
    {
      "name": "松屋",
      "group": "松屋フーズホールディングス",
      "aliases": [
        "まつや",
        "松弁ネット",
        "松屋モバイルオーダー"
      ],
      "conditions": {
        "payment_method": "店頭券売機・セルフレジでのカード決済、Apple Pay(QUICPay)、オンライン決済が対象。",
        "mobile_order": "松弁ネット、松屋モバイルオーダー対象",
        "delivery": "松弁デリバリー対象",
        "note": "高速道路SA・PA内店舗は対象外の場合あり。公式オンラインショップは対象外。Amexは条件が異なる可能性があるため公式サイトを確認推奨。"
      },
      "official_list_url": null,
      "card_type": "MUFG",
      "source_url": "https://www.cr.mufg.jp/mufgcard/point/global/save/convenience_store/index.html"
    },
    {
      "name": "松のや",
      "group": "松屋フーズホールディングス",
      "aliases": [
        "まつのや",
        "松乃家"
      ],
      "conditions": {
        "payment_method": "店頭券売機・セルフレジでのカード決済、Apple Pay(QUICPay)、オンライン決済が対象。",
        "mobile_order": "松弁ネット、松屋モバイルオーダー対象",
        "delivery": "松弁デリバリー対象",
        "note": "高速道路SA・PA内店舗は対象外の場合あり。Amexは条件が異なる可能性があるため公式サイトを確認推奨。"
      },
      "official_list_url": null,
      "card_type": "MUFG",
      "source_url": "https://www.cr.mufg.jp/mufgcard/point/global/save/convenience_store/index.html"
    },
    {
      "name": "マイカリー食堂",
      "group": "松屋フーズホールディングス",
      "aliases": [
        "まいかりーしょくどう"
      ],
      "conditions": {
        "payment_method": "店頭券売機・セルフレジでのカード決済、Apple Pay(QUICPay)、オンライン決済が対象。",
        "mobile_order": "松弁ネット、松屋モバイルオーダー対象",
        "delivery": "松弁デリバリー対象",
        "note": "高速道路SA・PA内店舗は対象外の場合あり。Amexは条件が異なる可能性があるため公式サイトを確認推奨。"
      },
      "official_list_url": null,
      "card_type": "MUFG",
      "source_url": "https://www.cr.mufg.jp/mufgcard/point/global/save/convenience_store/index.html"
    },
    {
      "name": "ゼッテリア",
      "group": "ゼンショーホールディングス",
      "aliases": [
        "ぜってりあ"
      ],
      "conditions": {
        "payment_method": "店頭決済、公式アプリでのモバイルオーダーが対象。",
        "mobile_order": "公式アプリ対象",
        "delivery": null,
        "note": "商業施設内の店舗は対象外の場合あり。ロッテリア店頭決済はAmex利用時は対象外。Amexは条件が異なる可能性があるため公式サイトを確認推奨。"
      },
      "official_list_url": null,
      "card_type": "MUFG",
      "source_url": "https://www.cr.mufg.jp/mufgcard/point/global/save/convenience_store/index.html"
    },
    {
      "name": "アオキスーパー",
      "group": null,
      "aliases": [
        "あおきすーぱー"
      ],
      "conditions": {
        "payment_method": "物理カード、カードのタッチ決済、Apple Pay(QUICPay)が対象。スマホのタッチ決済は対象外。",
        "mobile_order": "対象外",
        "delivery": "対象外",
        "note": "ショッピングセンターアズパーク内専門店、花いちばアズガーデンは対象外。Amexは条件が異なる可能性があるため公式サイトを確認推奨。"
      },
      "official_list_url": null,
      "card_type": "MUFG",
      "source_url": "https://www.cr.mufg.jp/mufgcard/point/global/save/convenience_store/index.html"
    },
    {
      "name": "オーケー",
      "group": "オーケー",
      "aliases": [
        "おーけー",
        "OKストア",
        "オーケーストア"
      ],
      "conditions": {
        "payment_method": "物理カード、カードのタッチ決済、Apple Pay(QUICPay)が対象。スマホのタッチ決済は対象外。",
        "mobile_order": "対象外",
        "delivery": "対象外",
        "note": "ネットスーパーは対象外。Amexは条件が異なる可能性があるため公式サイトを確認推奨。"
      },
      "official_list_url": null,
      "card_type": "MUFG",
      "source_url": "https://www.cr.mufg.jp/mufgcard/point/global/save/convenience_store/index.html"
    },
    {
      "name": "オオゼキ",
      "group": null,
      "aliases": [
        "おおぜき"
      ],
      "conditions": {
        "payment_method": "物理カード、カードのタッチ決済、Apple Pay(QUICPay)が対象。スマホのタッチ決済は対象外。",
        "mobile_order": "対象外",
        "delivery": "対象外",
        "note": "オンラインストア、ネットスーパーは対象外。Amexは条件が異なる可能性があるため公式サイトを確認推奨。"
      },
      "official_list_url": null,
      "card_type": "MUFG",
      "source_url": "https://www.cr.mufg.jp/mufgcard/point/global/save/convenience_store/index.html"
    },
    {
      "name": "サンリブ",
      "group": "サンリブグループ",
      "aliases": [
        "さんりぶ",
        "マルショク",
        "リブホール",
        "サンク",
        "サンリブBUONO",
        "まるしょく"
      ],
      "conditions": {
        "payment_method": "物理カード、カードのタッチ決済、Apple Pay(QUICPay)が対象。スマホのタッチ決済は対象外。",
        "mobile_order": "対象外",
        "delivery": "対象外",
        "note": "ネットスーパーは対象外。Amexは条件が異なる可能性があるため公式サイトを確認推奨。"
      },
      "official_list_url": null,
      "card_type": "MUFG",
      "source_url": "https://www.cr.mufg.jp/mufgcard/point/global/save/convenience_store/index.html"
    },
    {
      "name": "三和・フードワン",
      "group": "三和",
      "aliases": [
        "さんわ",
        "ふーどわん",
        "スーパー三和"
      ],
      "conditions": {
        "payment_method": "物理カード、カードのタッチ決済、Apple Pay(QUICPay)が対象。スマホのタッチ決済は対象外。",
        "mobile_order": "対象外",
        "delivery": "対象外",
        "note": "Amexは条件が異なる可能性があるため公式サイトを確認推奨。"
      },
      "official_list_url": null,
      "card_type": "MUFG",
      "source_url": "https://www.cr.mufg.jp/mufgcard/point/global/save/convenience_store/index.html"
    },
    {
      "name": "スーパー魚長",
      "group": null,
      "aliases": [
        "すーぱーうおちょう",
        "生鮮乃木市場",
        "生鮮げんだ市場",
        "うおちょう"
      ],
      "conditions": {
        "payment_method": "物理カード、カードのタッチ決済、Apple Pay(QUICPay)が対象。スマホのタッチ決済は対象外。",
        "mobile_order": "対象外",
        "delivery": "対象外",
        "note": "Amexは条件が異なる可能性があるため公式サイトを確認推奨。"
      },
      "official_list_url": null,
      "card_type": "MUFG",
      "source_url": "https://www.cr.mufg.jp/mufgcard/point/global/save/convenience_store/index.html"
    },
    {
      "name": "近商ストア",
      "group": "近鉄グループ",
      "aliases": [
        "きんしょうすとあ",
        "ハーベス",
        "Pochette",
        "はーべす",
        "ぽしぇっと"
      ],
      "conditions": {
        "payment_method": "物理カード、カードのタッチ決済、Apple Pay(QUICPay)が対象。スマホのタッチ決済は対象外。",
        "mobile_order": "対象外",
        "delivery": "対象外",
        "note": "ネットスーパー、食品スーパー以外での利用は対象外。Amexは条件が異なる可能性があるため公式サイトを確認推奨。"
      },
      "official_list_url": null,
      "card_type": "MUFG",
      "source_url": "https://www.cr.mufg.jp/mufgcard/point/global/save/convenience_store/index.html"
    },
    {
      "name": "東急ストア",
      "group": "東急グループ",
      "aliases": [
        "とうきゅうすとあ",
        "プレッセ",
        "フードステーション",
        "ぷれっせ"
      ],
      "conditions": {
        "payment_method": "物理カード、カードのタッチ決済、Apple Pay(QUICPay)が対象。スマホのタッチ決済は対象外。",
        "mobile_order": "対象外",
        "delivery": "対象外",
        "note": "テナント、ネットスーパーは対象外。Amexは条件が異なる可能性があるため公式サイトを確認推奨。"
      },
      "official_list_url": null,
      "card_type": "MUFG",
      "source_url": "https://www.cr.mufg.jp/mufgcard/point/global/save/convenience_store/index.html"
    },
    {
      "name": "東武ストア",
      "group": "東武グループ",
      "aliases": [
        "とうぶすとあ"
      ],
      "conditions": {
        "payment_method": "物理カード、カードのタッチ決済、Apple Pay(QUICPay)が対象。スマホのタッチ決済は対象外。",
        "mobile_order": "対象外",
        "delivery": "対象外",
        "note": "ネットショップ、手ぶら決済、専門店売り場は対象外。Amexは条件が異なる可能性があるため公式サイトを確認推奨。"
      },
      "official_list_url": null,
      "card_type": "MUFG",
      "source_url": "https://www.cr.mufg.jp/mufgcard/point/global/save/convenience_store/index.html"
    },
    {
      "name": "ドミー",
      "group": null,
      "aliases": [
        "どみー"
      ],
      "conditions": {
        "payment_method": "物理カード、カードのタッチ決済、Apple Pay(QUICPay)が対象。スマホのタッチ決済は対象外。",
        "mobile_order": "対象外",
        "delivery": "対象外",
        "note": "Amexは条件が異なる可能性があるため公式サイトを確認推奨。"
      },
      "official_list_url": null,
      "card_type": "MUFG",
      "source_url": "https://www.cr.mufg.jp/mufgcard/point/global/save/convenience_store/index.html"
    },
    {
      "name": "肉のハナマサ",
      "group": "ジェーシー・コムサ",
      "aliases": [
        "にくのはなまさ",
        "ハナマサ",
        "はなまさ"
      ],
      "conditions": {
        "payment_method": "物理カード、カードのタッチ決済、Apple Pay(QUICPay)が対象。スマホのタッチ決済は対象外。",
        "mobile_order": "対象外",
        "delivery": "対象外",
        "note": "フランチャイズ店は対象外。Amexは条件が異なる可能性があるため公式サイトを確認推奨。"
      },
      "official_list_url": null,
      "card_type": "MUFG",
      "source_url": "https://www.cr.mufg.jp/mufgcard/point/global/save/convenience_store/index.html"
    },
    {
      "name": "ジャパンミート",
      "group": "JMホールディングス",
      "aliases": [
        "じゃぱんみーと",
        "MEATMeet",
        "パワーマート",
        "ぱわーまーと"
      ],
      "conditions": {
        "payment_method": "物理カード、カードのタッチ決済、Apple Pay(QUICPay)が対象。スマホのタッチ決済は対象外。",
        "mobile_order": "対象外",
        "delivery": "対象外",
        "note": "Amexは条件が異なる可能性があるため公式サイトを確認推奨。"
      },
      "official_list_url": null,
      "card_type": "MUFG",
      "source_url": "https://www.cr.mufg.jp/mufgcard/point/global/save/convenience_store/index.html"
    },
    {
      "name": "ヤマナカ",
      "group": null,
      "aliases": [
        "やまなか",
        "フランテ",
        "フランテロゼ",
        "ふらんて"
      ],
      "conditions": {
        "payment_method": "物理カード、カードのタッチ決済、Apple Pay(QUICPay)が対象。スマホのタッチ決済は対象外。",
        "mobile_order": "対象外",
        "delivery": "対象外",
        "note": "ネットスーパーは対象外。Amexは条件が異なる可能性があるため公式サイトを確認推奨。"
      },
      "official_list_url": null,
      "card_type": "MUFG",
      "source_url": "https://www.cr.mufg.jp/mufgcard/point/global/save/convenience_store/index.html"
    }
  ]
}